pepperize_cdk_vpc/__init__.py
pepperize_cdk_vpc/py.typed
pepperize_cdk_vpc/_jsii/__init__.py
pepperize_cdk_vpc/_jsii/cdk-vpc@0.0.1165.jsii.tgz
pepperize_cdk_vpc-0.0.1165.dist-info/LICENSE
pepperize_cdk_vpc-0.0.1165.dist-info/METADATA
pepperize_cdk_vpc-0.0.1165.dist-info/WHEEL
pepperize_cdk_vpc-0.0.1165.dist-info/top_level.txt
pepperize_cdk_vpc-0.0.1165.dist-info/RECORD
